AUTHORS.rst
CONTRIBUTING.rst
HISTORY.rst
LICENSE
MANIFEST.in
README.rst
setup.cfg
setup.py
docs/Makefile
docs/authors.rst
docs/conf.py
docs/contributing.rst
docs/history.rst
docs/index.rst
docs/installation.rst
docs/make.bat
docs/readme.rst
docs/usage.rst
pipreqs/__init__.py
pipreqs/mapping
pipreqs/pipreqs.py
pipreqs/stdlib
pipreqs_amasad.egg-info/PKG-INFO
pipreqs_amasad.egg-info/SOURCES.txt
pipreqs_amasad.egg-info/dependency_links.txt
pipreqs_amasad.egg-info/entry_points.txt
pipreqs_amasad.egg-info/not-zip-safe
pipreqs_amasad.egg-info/requires.txt
pipreqs_amasad.egg-info/top_level.txt
tests/__init__.py
tests/test_pipreqs.py
tests/_data/models.py
tests/_data/test.py
tests/_data_duplicated_deps/db.py
tests/_data_ignore/test.py
tests/_data_ignore/.ignore_second/ignored.py
tests/_data_ignore/.ignored_dir/ignored.py
tests/_invalid_data/invalid.py