Metadata-Version: 1.1
Name: pipreqs-amasad
Version: 0.4.9
Summary: Pip requirements.txt generator based on imports in project
Home-page: https://github.com/amasad/pipreqs
Author: Amjad Masad
Author-email: amjad.masad@gmail.com
License: Apache License
Keywords: pip requirements imports
Platform: UNKNOWN
Classifier: Development Status :: 4 - Beta
Classifier: Intended Audience :: Developers
Classifier: License :: OSI Approved :: Apache Software License
Classifier: Natural Language :: English
Classifier: Programming Language :: Python :: 2
Classifier: Programming Language :: Python :: 2.7
Classifier: Programming Language :: Python :: 3
Classifier: Programming Language :: Python :: 3.4
Classifier: Programming Language :: Python :: 3.5
Classifier: Programming Language :: Python :: 3.6
